napari_curviewer/__init__.py
napari_curviewer/_reader.py
napari_curviewer/_sample_data.py
napari_curviewer/_version.py
napari_curviewer/_widget.py
napari_curviewer/_writer.py
napari_curviewer/napari.yaml
napari_curviewer/_tests/__init__.py
napari_curviewer/_tests/test_reader.py
napari_curviewer/_tests/test_sample_data.py
napari_curviewer/_tests/test_widget.py
napari_curviewer/_tests/test_writer.py
napari_curviewer-0.1.0.dist-info/LICENSE
napari_curviewer-0.1.0.dist-info/METADATA
napari_curviewer-0.1.0.dist-info/WHEEL
napari_curviewer-0.1.0.dist-info/entry_points.txt
napari_curviewer-0.1.0.dist-info/top_level.txt
napari_curviewer-0.1.0.dist-info/RECORD
