Metadata-Version: 2.1
Name: napari-curviewer
Version: 0.1.0
Summary: A plugin to unroll organs along their curved central line
Home-page: https://github.com/Rocsg/napari-curviewer
Author: Romain Fernandez
Author-email: romain.fernandez@cirad.fr
License: LGPL-3.0-only
Project-URL: Bug Tracker, https://github.com/Rocsg/napari-curviewer/issues
Project-URL: Documentation, https://github.com/Rocsg/napari-curviewer#README.md
Project-URL: Source Code, https://github.com/Rocsg/napari-curviewer
Project-URL: User Support, https://github.com/Rocsg/napari-curviewer/issues
Classifier: Development Status :: 2 - Pre-Alpha
Classifier: Framework :: napari
Classifier: Intended Audience :: Developers
Classifier: License :: OSI Approved :: GNU Lesser General Public License v3 (LGPLv3)
Classifier: Operating System :: OS Independent
Classifier: Programming Language :: Python
Classifier: Programming Language :: Python :: 3
Classifier: Programming Language :: Python :: 3 :: Only
Classifier: Programming Language :: Python :: 3.8
Classifier: Programming Language :: Python :: 3.9
Classifier: Programming Language :: Python :: 3.10
Classifier: Topic :: Scientific/Engineering :: Image Processing
Requires-Python: >=3.8
License-File: LICENSE
Requires-Dist: numpy
Requires-Dist: magicgui
Requires-Dist: qtpy
Requires-Dist: scikit-image
Requires-Dist: vedo
Requires-Dist: vtk
Requires-Dist: scipy
Provides-Extra: testing
Requires-Dist: tox ; extra == 'testing'
Requires-Dist: pytest ; extra == 'testing'
Requires-Dist: pytest-cov ; extra == 'testing'
Requires-Dist: pytest-qt ; extra == 'testing'
Requires-Dist: napari ; extra == 'testing'
Requires-Dist: pyqt5 ; extra == 'testing'
